{
  "directed": false,
  "multigraph": false,
  "graph": {},
  "nodes": [
    {
      "label": "CVMError",
      "file_type": "code",
      "source_file": "include/error.hpp",
      "source_location": null,
      "source_url": null,
      "captured_at": null,
      "author": null,
      "contributor": null,
      "id": "cvmpp_cvm_error",
      "community": 1,
      "norm_label": "cvmerror"
    },
    {
      "label": "LexError",
      "file_type": "code",
      "source_file": "include/error.hpp",
      "source_location": null,
      "source_url": null,
      "captured_at": null,
      "author": null,
      "contributor": null,
      "id": "cvmpp_lex_error",
      "community": 1,
      "norm_label": "lexerror"
    },
    {
      "label": "ParseError",
      "file_type": "code",
      "source_file": "include/error.hpp",
      "source_location": null,
      "source_url": null,
      "captured_at": null,
      "author": null,
      "contributor": null,
      "id": "cvmpp_parse_error",
      "community": 1,
      "norm_label": "parseerror"
    },
    {
      "label": "CompileError",
      "file_type": "code",
      "source_file": "include/error.hpp",
      "source_location": null,
      "source_url": null,
      "captured_at": null,
      "author": null,
      "contributor": null,
      "id": "cvmpp_compile_error",
      "community": 1,
      "norm_label": "compileerror"
    },
    {
      "label": "RuntimeError",
      "file_type": "code",
      "source_file": "include/error.hpp",
      "source_location": null,
      "source_url": null,
      "captured_at": null,
      "author": null,
      "contributor": null,
      "id": "cvmpp_runtime_error",
      "community": 1,
      "norm_label": "runtimeerror"
    },
    {
      "label": "TokenType",
      "file_type": "code",
      "source_file": "include/token.hpp",
      "source_location": null,
      "source_url": null,
      "captured_at": null,
      "author": null,
      "contributor": null,
      "id": "cvmpp_token_type",
      "community": 0,
      "norm_label": "tokentype"
    },
    {
      "label": "Token",
      "file_type": "code",
      "source_file": "include/token.hpp",
      "source_location": null,
      "source_url": null,
      "captured_at": null,
      "author": null,
      "contributor": null,
      "id": "cvmpp_token",
      "community": 0,
      "norm_label": "token"
    },
    {
      "label": "Value",
      "file_type": "code",
      "source_file": "include/value.hpp",
      "source_location": null,
      "source_url": null,
      "captured_at": null,
      "author": null,
      "contributor": null,
      "id": "cvmpp_value",
      "community": 2,
      "norm_label": "value"
    },
    {
      "label": "OpCode",
      "file_type": "code",
      "source_file": "include/chunk.hpp",
      "source_location": null,
      "source_url": null,
      "captured_at": null,
      "author": null,
      "contributor": null,
      "id": "cvmpp_op_code",
      "community": 2,
      "norm_label": "opcode"
    },
    {
      "label": "Chunk",
      "file_type": "code",
      "source_file": "include/chunk.hpp",
      "source_location": null,
      "source_url": null,
      "captured_at": null,
      "author": null,
      "contributor": null,
      "id": "cvmpp_chunk",
      "community": 2,
      "norm_label": "chunk"
    },
    {
      "label": "Expr",
      "file_type": "code",
      "source_file": "include/ast.hpp",
      "source_location": null,
      "source_url": null,
      "captured_at": null,
      "author": null,
      "contributor": null,
      "id": "cvmpp_expr",
      "community": 0,
      "norm_label": "expr"
    },
    {
      "label": "Stmt",
      "file_type": "code",
      "source_file": "include/ast.hpp",
      "source_location": null,
      "source_url": null,
      "captured_at": null,
      "author": null,
      "contributor": null,
      "id": "cvmpp_stmt",
      "community": 0,
      "norm_label": "stmt"
    },
    {
      "label": "Program",
      "file_type": "code",
      "source_file": "include/ast.hpp",
      "source_location": null,
      "source_url": null,
      "captured_at": null,
      "author": null,
      "contributor": null,
      "id": "cvmpp_program",
      "community": 0,
      "norm_label": "program"
    },
    {
      "label": "VM",
      "file_type": "code",
      "source_file": "include/vm.hpp",
      "source_location": null,
      "source_url": null,
      "captured_at": null,
      "author": null,
      "contributor": null,
      "id": "cvmpp_vm",
      "community": 2,
      "norm_label": "vm"
    },
    {
      "label": "Lexer",
      "file_type": "code",
      "source_file": "src/lexer.cpp",
      "source_location": null,
      "source_url": null,
      "captured_at": null,
      "author": null,
      "contributor": null,
      "id": "cvmpp_lexer",
      "community": 0,
      "norm_label": "lexer"
    },
    {
      "label": "Parser",
      "file_type": "code",
      "source_file": "src/parser.cpp",
      "source_location": null,
      "source_url": null,
      "captured_at": null,
      "author": null,
      "contributor": null,
      "id": "cvmpp_parser",
      "community": 0,
      "norm_label": "parser"
    },
    {
      "label": "Compiler",
      "file_type": "code",
      "source_file": "src/compiler.cpp",
      "source_location": null,
      "source_url": null,
      "captured_at": null,
      "author": null,
      "contributor": null,
      "id": "cvmpp_compiler",
      "community": 0,
      "norm_label": "compiler"
    }
  ],
  "links": [
    {
      "relation": "implements",
      "confidence": "EXTRACTED",
      "confidence_score": 1.0,
      "source_file": "include/error.hpp",
      "source_location": null,
      "weight": 1.0,
      "source": "cvmpp_lex_error",
      "target": "cvmpp_cvm_error"
    },
    {
      "relation": "implements",
      "confidence": "EXTRACTED",
      "confidence_score": 1.0,
      "source_file": "include/error.hpp",
      "source_location": null,
      "weight": 1.0,
      "source": "cvmpp_parse_error",
      "target": "cvmpp_cvm_error"
    },
    {
      "relation": "implements",
      "confidence": "EXTRACTED",
      "confidence_score": 1.0,
      "source_file": "include/error.hpp",
      "source_location": null,
      "weight": 1.0,
      "source": "cvmpp_compile_error",
      "target": "cvmpp_cvm_error"
    },
    {
      "relation": "implements",
      "confidence": "EXTRACTED",
      "confidence_score": 1.0,
      "source_file": "include/error.hpp",
      "source_location": null,
      "weight": 1.0,
      "source": "cvmpp_runtime_error",
      "target": "cvmpp_cvm_error"
    },
    {
      "relation": "references",
      "confidence": "EXTRACTED",
      "confidence_score": 1.0,
      "source_file": "src/vm.cpp",
      "source_location": null,
      "weight": 1.0,
      "source": "cvmpp_vm",
      "target": "cvmpp_runtime_error"
    },
    {
      "relation": "references",
      "confidence": "EXTRACTED",
      "confidence_score": 1.0,
      "source_file": "include/token.hpp",
      "source_location": null,
      "weight": 1.0,
      "source": "cvmpp_token",
      "target": "cvmpp_token_type"
    },
    {
      "relation": "references",
      "confidence": "INFERRED",
      "confidence_score": 0.9,
      "source_file": "include/ast.hpp",
      "source_location": null,
      "weight": 1.0,
      "source": "cvmpp_expr",
      "target": "cvmpp_token"
    },
    {
      "relation": "references",
      "confidence": "INFERRED",
      "confidence_score": 1.0,
      "source_file": "src/lexer.cpp",
      "source_location": null,
      "weight": 1.0,
      "source": "cvmpp_lexer",
      "target": "cvmpp_token"
    },
    {
      "relation": "references",
      "confidence": "INFERRED",
      "confidence_score": 1.0,
      "source_file": "src/parser.cpp",
      "source_location": null,
      "weight": 1.0,
      "source": "cvmpp_parser",
      "target": "cvmpp_token"
    },
    {
      "relation": "shares_data_with",
      "confidence": "EXTRACTED",
      "confidence_score": 1.0,
      "source_file": "include/chunk.hpp",
      "source_location": null,
      "weight": 1.0,
      "source": "cvmpp_chunk",
      "target": "cvmpp_value"
    },
    {
      "relation": "shares_data_with",
      "confidence": "EXTRACTED",
      "confidence_score": 1.0,
      "source_file": "include/vm.hpp",
      "source_location": null,
      "weight": 1.0,
      "source": "cvmpp_vm",
      "target": "cvmpp_value"
    },
    {
      "relation": "references",
      "confidence": "EXTRACTED",
      "confidence_score": 1.0,
      "source_file": "include/chunk.hpp",
      "source_location": null,
      "weight": 1.0,
      "source": "cvmpp_chunk",
      "target": "cvmpp_op_code"
    },
    {
      "relation": "references",
      "confidence": "EXTRACTED",
      "confidence_score": 1.0,
      "source_file": "include/vm.hpp",
      "source_location": null,
      "weight": 1.0,
      "source": "cvmpp_vm",
      "target": "cvmpp_chunk"
    },
    {
      "relation": "references",
      "confidence": "INFERRED",
      "confidence_score": 1.0,
      "source_file": "src/compiler.cpp",
      "source_location": null,
      "weight": 1.0,
      "source": "cvmpp_compiler",
      "target": "cvmpp_chunk"
    },
    {
      "relation": "references",
      "confidence": "EXTRACTED",
      "confidence_score": 1.0,
      "source_file": "include/ast.hpp",
      "source_location": null,
      "weight": 1.0,
      "source": "cvmpp_stmt",
      "target": "cvmpp_expr"
    },
    {
      "relation": "references",
      "confidence": "EXTRACTED",
      "confidence_score": 1.0,
      "source_file": "include/ast.hpp",
      "source_location": null,
      "weight": 1.0,
      "source": "cvmpp_program",
      "target": "cvmpp_stmt"
    },
    {
      "relation": "references",
      "confidence": "INFERRED",
      "confidence_score": 1.0,
      "source_file": "src/parser.cpp",
      "source_location": null,
      "weight": 1.0,
      "source": "cvmpp_parser",
      "target": "cvmpp_program"
    },
    {
      "relation": "references",
      "confidence": "INFERRED",
      "confidence_score": 1.0,
      "source_file": "src/compiler.cpp",
      "source_location": null,
      "weight": 1.0,
      "source": "cvmpp_compiler",
      "target": "cvmpp_program"
    }
  ],
  "hyperedges": [],
  "built_at_commit": "63d5cd8e975222a0bea560b1220766625f2f1ed8"
}